langgraph_dynamodb_checkpoint/LICENSE
langgraph_dynamodb_checkpoint/__init__.py
langgraph_dynamodb_checkpoint/dynamodbSaver.py
langgraph_dynamodb_checkpoint/dynamodbSerializer.py
langgraph_dynamodb_checkpoint/logger.py
langgraph_dynamodb_checkpoint-0.2.6.2.dist-info/METADATA
langgraph_dynamodb_checkpoint-0.2.6.2.dist-info/WHEEL
langgraph_dynamodb_checkpoint-0.2.6.2.dist-info/RECORD
