Metadata-Version: 2.4
Name: langgraph_dynamodb_checkpoint
Version: 0.2.6.2
Summary: DynamoDB checkpoint saver implementation for LangGraph - Single table, auto create with delete handling
Project-URL: Homepage, https://github.com/skamalj/langgraph_dynamodb_checkpoint
Project-URL: Documentation, https://readthedocs.org
Project-URL: Repository, https://github.com/skamalj/langgraph_dynamodb_checkpoint.git
Project-URL: Issues, https://github.com/skamalj/langgraph_dynamodb_checkpoint/issues
Project-URL: Changelog, https://github.com/skamalj/langgraph_dynamodb_checkpoint/blob/main/CHANGELOG.md
Author-email: Kamal <skamalj@github.com>
Classifier: License :: OSI Approved :: MIT License
Classifier: Operating System :: OS Independent
Classifier: Programming Language :: Python :: 3
Requires-Python: >=3.9
Requires-Dist: boto3
Requires-Dist: botocore
Requires-Dist: langchain-core
Requires-Dist: langgraph
Provides-Extra: dev
Requires-Dist: black; extra == 'dev'
Requires-Dist: isort; extra == 'dev'
Requires-Dist: mypy; extra == 'dev'
Requires-Dist: pytest-cov; extra == 'dev'
Requires-Dist: pytest>=7.0; extra == 'dev'
